Doxyfile
LICENSE
README
setup.py
examples/cycle_metanet.py
examples/mnist.py
examples/opposed.py
examples/pred_example.py
examples/simple_metanet.py
examples/xor.py
metanet/__init__.py
metanet.egg-info/PKG-INFO
metanet.egg-info/SOURCES.txt
metanet.egg-info/dependency_links.txt
metanet.egg-info/requires.txt
metanet.egg-info/top_level.txt
metanet/datasets/__init__.py
metanet/datasets/iris.py
metanet/datasets/mnist.py
metanet/datasets/xor.py
metanet/networks/__init__.py
metanet/networks/metanet.py
metanet/networks/artificial_networks/__init__.py
metanet/networks/artificial_networks/feedforward_network.py
metanet/networks/artificial_networks/hopfield_network.py
metanet/networks/artificial_networks/opposed_network.py
metanet/networks/connections/__init__.py
metanet/networks/connections/connect_rule.py
metanet/networks/groups/__init__.py
metanet/networks/groups/group.py
metanet/networks/nodes/__init__.py
metanet/networks/nodes/network.py
metanet/networks/nodes/neuron.py
metanet/networks/nodes/node.py
metanet/tests/__init__.py
metanet/tests/test_feedforwardNetwork.py