Metadata-Version: 1.0
Name: metanet
Version: 0.1
Summary: Free portable library for meta neural network research
Home-page: UNKNOWN
Author: UNKNOWN
Author-email: UNKNOWN
License: GPL3
Platform: UNKNOWN
